Java9MokuaihuaKaifaFix1/README.md
Java9MokuaihuaKaifaFix1/__init__.py
Java9MokuaihuaKaifaFix1/__main__.py
Java9MokuaihuaKaifaFix1/file.epub
Java9MokuaihuaKaifaFix1/index.html
Java9MokuaihuaKaifaFix1/css/__init__.py
Java9MokuaihuaKaifaFix1/css/annotations.css
Java9MokuaihuaKaifaFix1/css/main.css
Java9MokuaihuaKaifaFix1/css/normalize.css
Java9MokuaihuaKaifaFix1/css/popup.css
Java9MokuaihuaKaifaFix1/font/__init__.py
Java9MokuaihuaKaifaFix1/font/fontello.eot
Java9MokuaihuaKaifaFix1/font/fontello.svg
Java9MokuaihuaKaifaFix1/font/fontello.ttf
Java9MokuaihuaKaifaFix1/font/fontello.woff
Java9MokuaihuaKaifaFix1/img/__init__.py
Java9MokuaihuaKaifaFix1/img/annotator-glyph-sprite.png
Java9MokuaihuaKaifaFix1/img/annotator-icon-sprite.png
Java9MokuaihuaKaifaFix1/img/apple-touch-icon.png
Java9MokuaihuaKaifaFix1/img/cancelfullscreen.png
Java9MokuaihuaKaifaFix1/img/close.png
Java9MokuaihuaKaifaFix1/img/fullscreen.png
Java9MokuaihuaKaifaFix1/img/loader.gif
Java9MokuaihuaKaifaFix1/img/menu-icon.png
Java9MokuaihuaKaifaFix1/img/save.png
Java9MokuaihuaKaifaFix1/img/saved.png
Java9MokuaihuaKaifaFix1/img/settings-s.png
Java9MokuaihuaKaifaFix1/img/settings.png
Java9MokuaihuaKaifaFix1/img/star.png
Java9MokuaihuaKaifaFix1/js/__init__.py
Java9MokuaihuaKaifaFix1/js/epub.js
Java9MokuaihuaKaifaFix1/js/epub.min.js
Java9MokuaihuaKaifaFix1/js/epub.min.map
Java9MokuaihuaKaifaFix1/js/hooks.min.js
Java9MokuaihuaKaifaFix1/js/hooks.min.map
Java9MokuaihuaKaifaFix1/js/reader.js
Java9MokuaihuaKaifaFix1/js/reader.js.map
Java9MokuaihuaKaifaFix1/js/reader.min.js
Java9MokuaihuaKaifaFix1/js/reader.min.map
Java9MokuaihuaKaifaFix1/js/hooks/__init__.py
Java9MokuaihuaKaifaFix1/js/hooks/extensions/__init__.py
Java9MokuaihuaKaifaFix1/js/hooks/extensions/highlight.js
Java9MokuaihuaKaifaFix1/js/libs/__init__.py
Java9MokuaihuaKaifaFix1/js/libs/jquery.min.js
Java9MokuaihuaKaifaFix1/js/libs/localforage.min.js
Java9MokuaihuaKaifaFix1/js/libs/screenfull.js
Java9MokuaihuaKaifaFix1/js/libs/screenfull.min.js
java_9_mokuaihua_kaifa_fix1-2025.3.24.0.dist-info/METADATA
java_9_mokuaihua_kaifa_fix1-2025.3.24.0.dist-info/WHEEL
java_9_mokuaihua_kaifa_fix1-2025.3.24.0.dist-info/entry_points.txt
java_9_mokuaihua_kaifa_fix1-2025.3.24.0.dist-info/top_level.txt
java_9_mokuaihua_kaifa_fix1-2025.3.24.0.dist-info/RECORD
